PyILP/PyILP.py
PyILP/__init__.py
PyILP-0.0.2.dist-info/METADATA
PyILP-0.0.2.dist-info/WHEEL
PyILP-0.0.2.dist-info/top_level.txt
PyILP-0.0.2.dist-info/RECORD
